{ 
    "_id" : ObjectId("5d81c9580652631074e21cbf"), 
    "uid" : NumberInt(2), 
    "orderid" : "345", 
    "date" : "18/8/2019-11:36", 
    "status" : "Pending"
}
{ 
    "_id" : ObjectId("5d81cab60652631074e21cc7"), 
    "uid" : NumberInt(2), 
    "orderid" : "11223344", 
    "date" : "18/8/2019-11:42", 
    "status" : "Pending"
}
{ 
    "_id" : ObjectId("5d81cca40652631074e21cc8"), 
    "uid" : NumberInt(2), 
    "orderid" : "345", 
    "date" : "18/8/2019-11:50", 
    "status" : "Pending"
}
{ 
    "_id" : ObjectId("5d81d7890652631074e21cc9"), 
    "uid" : NumberInt(2), 
    "orderid" : "345", 
    "date" : "18/8/2019-12:36", 
    "status" : "Pending"
}
{ 
    "_id" : ObjectId("5d81e2a7e737b13f60cbbffa"), 
    "uid" : NumberInt(2), 
    "orderid" : "345", 
    "date" : "18/8/2019-13:24", 
    "status" : "Pending"
}
{ 
    "_id" : ObjectId("5d81e9b5cc8a280744888f07"), 
    "uid" : NumberInt(2), 
    "orderid" : "345", 
    "date" : "18/8/2019-13:54", 
    "status" : "Pending"
}
{ 
    "_id" : ObjectId("5d81eaebd298ee4cd832f7a9"), 
    "uid" : NumberInt(1), 
    "orderid" : "345", 
    "date" : "18/8/2019-13:59", 
    "status" : "Pending"
}
{ 
    "_id" : ObjectId("5d81eb83d298ee4cd832f7ac"), 
    "uid" : NumberInt(1), 
    "orderid" : "345", 
    "date" : "18/8/2019-14:2", 
    "status" : "Pending"
}
{ 
    "_id" : ObjectId("5d81ebbdd298ee4cd832f7ad"), 
    "uid" : NumberInt(1), 
    "orderid" : "345", 
    "date" : "18/8/2019-14:3", 
    "status" : "Pending"
}
{ 
    "_id" : ObjectId("5d81ed2bcd2079141c9d59d2"), 
    "uid" : NumberInt(1), 
    "orderid" : "345", 
    "date" : "18/8/2019-14:9", 
    "status" : "Pending"
}
{ 
    "_id" : ObjectId("5d81ed2bcd2079141c9d59d3"), 
    "uid" : NumberInt(1), 
    "orderid" : "345", 
    "date" : "18/8/2019-14:9", 
    "status" : "Pending"
}
{ 
    "_id" : ObjectId("5d81ed2bcd2079141c9d59d4"), 
    "uid" : NumberInt(1), 
    "orderid" : "345", 
    "date" : "18/8/2019-14:9", 
    "status" : "Pending"
}
{ 
    "_id" : ObjectId("5d81ed2bcd2079141c9d59d5"), 
    "uid" : NumberInt(1), 
    "orderid" : "345", 
    "date" : "18/8/2019-14:9", 
    "status" : "Pending"
}
{ 
    "_id" : ObjectId("5d81ed6675b3323810663c2b"), 
    "uid" : NumberInt(1), 
    "orderid" : "345", 
    "date" : "18/8/2019-14:10", 
    "status" : "Pending"
}
{ 
    "_id" : ObjectId("5d8308c30e40d6425c84dbaf"), 
    "uid" : NumberInt(1), 
    "orderid" : "345", 
    "date" : "19/8/2019-10:19", 
    "status" : "Pending"
}
{ 
    "_id" : ObjectId("5d830de18c165d19f476a35e"), 
    "uid" : NumberInt(1), 
    "orderid" : "345", 
    "date" : "19/8/2019-10:40", 
    "status" : "Pending"
}
{ 
    "_id" : ObjectId("5d8311182ff10147403b55f9"), 
    "uid" : NaN, 
    "orderid" : "345", 
    "date" : "19/8/2019-10:54", 
    "status" : "Pending"
}
{ 
    "_id" : ObjectId("5d831219ed42d056e02fbbad"), 
    "uid" : NaN, 
    "orderid" : "345", 
    "date" : "19/8/2019-10:58", 
    "status" : "Pending"
}
{ 
    "_id" : ObjectId("5d8316fc2af4bd181c545c3d"), 
    "uid" : NaN, 
    "orderid" : "345", 
    "date" : "19/8/2019-11:19", 
    "status" : "Pending"
}
{ 
    "_id" : ObjectId("5d8318177ca9c810983ff0ee"), 
    "uid" : NaN, 
    "orderid" : "345", 
    "date" : "19/8/2019-11:24", 
    "status" : "Pending"
}
{ 
    "_id" : ObjectId("5d831896c7b3eb5514764d53"), 
    "uid" : NaN, 
    "orderid" : "345", 
    "date" : "19/8/2019-11:26", 
    "status" : "Pending"
}
{ 
    "_id" : ObjectId("5d8319778d9c44543088af6a"), 
    "uid" : NaN, 
    "orderid" : "345", 
    "date" : "19/8/2019-11:30", 
    "status" : "Pending"
}
{ 
    "_id" : ObjectId("5d831a4b87022525185b626e"), 
    "uid" : NumberInt(2), 
    "orderid" : "345", 
    "date" : "19/8/2019-11:33", 
    "status" : "Pending"
}
{ 
    "_id" : ObjectId("5d831ac1e66a8a42f892295b"), 
    "uid" : NumberInt(2), 
    "orderid" : "345", 
    "date" : "19/8/2019-11:35", 
    "status" : "Pending"
}
{ 
    "_id" : ObjectId("5d831b1c41d85c0d4481d3a4"), 
    "uid" : NumberInt(1), 
    "orderid" : "345", 
    "date" : "19/8/2019-11:37", 
    "status" : "Pending"
}
{ 
    "_id" : ObjectId("5d831ec6fa1aa907cc1e6f2c"), 
    "uid" : NumberInt(1), 
    "orderid" : "345", 
    "date" : "19/8/2019-11:53", 
    "status" : "Pending"
}
{ 
    "_id" : ObjectId("5d831f24fa1aa907cc1e6f2d"), 
    "uid" : NumberInt(1), 
    "orderid" : "345", 
    "date" : "19/8/2019-11:54", 
    "status" : "Pending"
}
{ 
    "_id" : ObjectId("5d831f35fa1aa907cc1e6f2e"), 
    "uid" : NumberInt(1), 
    "orderid" : "345", 
    "date" : "19/8/2019-11:54", 
    "status" : "Pending"
}
{ 
    "_id" : ObjectId("5d8320e9fa1aa907cc1e6f30"), 
    "uid" : NumberInt(1), 
    "orderid" : "345", 
    "date" : "19/8/2019-12:2", 
    "status" : "Pending"
}
{ 
    "_id" : ObjectId("5d832185dfa30d4e3876920d"), 
    "uid" : NumberInt(1), 
    "orderid" : "345", 
    "date" : "19/8/2019-12:4", 
    "status" : "Pending"
}
{ 
    "_id" : ObjectId("5d8321b1dfa30d4e3876920f"), 
    "uid" : NumberInt(1), 
    "orderid" : "345", 
    "date" : "19/8/2019-12:5", 
    "status" : "Pending"
}
{ 
    "_id" : ObjectId("5d8321eedfa30d4e38769210"), 
    "uid" : NumberInt(1), 
    "orderid" : "345", 
    "date" : "19/8/2019-12:6", 
    "status" : "Pending"
}
{ 
    "_id" : ObjectId("5d83221edfa30d4e38769212"), 
    "uid" : NumberInt(1), 
    "orderid" : "345", 
    "date" : "19/8/2019-12:7", 
    "status" : "Pending"
}
{ 
    "_id" : ObjectId("5d832236dfa30d4e38769213"), 
    "uid" : NumberInt(1), 
    "orderid" : "345", 
    "date" : "19/8/2019-12:7", 
    "status" : "Pending"
}
{ 
    "_id" : ObjectId("5d8322fadfa30d4e38769215"), 
    "uid" : NumberInt(1), 
    "orderid" : "345", 
    "date" : "19/8/2019-12:10", 
    "status" : "Pending"
}
{ 
    "_id" : ObjectId("5d83235ddfa30d4e38769216"), 
    "uid" : NumberInt(1), 
    "orderid" : "345", 
    "date" : "19/8/2019-12:12", 
    "status" : "Pending"
}
{ 
    "_id" : ObjectId("5d83236fdfa30d4e38769217"), 
    "uid" : NumberInt(1), 
    "orderid" : "345", 
    "date" : "19/8/2019-12:12", 
    "status" : "Pending"
}
{ 
    "_id" : ObjectId("5d832389dfa30d4e38769219"), 
    "uid" : NumberInt(1), 
    "orderid" : "345", 
    "date" : "19/8/2019-12:13", 
    "status" : "Pending"
}
{ 
    "_id" : ObjectId("5d832401bf5de52d3826a84a"), 
    "uid" : NumberInt(1), 
    "orderid" : "345", 
    "date" : "19/8/2019-12:15", 
    "status" : "Pending"
}
{ 
    "_id" : ObjectId("5d832494a715e0531cd18241"), 
    "uid" : NumberInt(1), 
    "orderid" : "345", 
    "date" : "19/8/2019-12:17", 
    "status" : "Pending"
}
{ 
    "_id" : ObjectId("5d83264825211a3a5c245e7a"), 
    "uid" : NumberInt(1), 
    "orderid" : "345", 
    "date" : "19/8/2019-12:25", 
    "status" : "Pending"
}
{ 
    "_id" : ObjectId("5d832699e5900b2598f7df4c"), 
    "uid" : NumberInt(1), 
    "orderid" : "345", 
    "date" : "19/8/2019-12:26", 
    "status" : "Pending"
}
{ 
    "_id" : ObjectId("5d8327071d7e48350016132e"), 
    "uid" : NumberInt(1), 
    "orderid" : "345", 
    "date" : "19/8/2019-12:28", 
    "status" : "Pending"
}
{ 
    "_id" : ObjectId("5d83273eb390d02578e2dd2c"), 
    "uid" : NumberInt(1), 
    "orderid" : "345", 
    "date" : "19/8/2019-12:29", 
    "status" : "Pending"
}
{ 
    "_id" : ObjectId("5d832784966b754b0cfc9a12"), 
    "uid" : NumberInt(1), 
    "orderid" : "345", 
    "date" : "19/8/2019-12:30", 
    "status" : "Pending"
}
{ 
    "_id" : ObjectId("5d83284118742d27b0617084"), 
    "uid" : NumberInt(1), 
    "orderid" : "345", 
    "date" : "19/8/2019-12:33", 
    "status" : "Pending"
}
{ 
    "_id" : ObjectId("5d83286a18742d27b0617086"), 
    "uid" : NumberInt(1), 
    "orderid" : "345", 
    "date" : "19/8/2019-12:34", 
    "status" : "Pending"
}
{ 
    "_id" : ObjectId("5d8328beb3fd4646045055cc"), 
    "uid" : NumberInt(1), 
    "orderid" : "345", 
    "date" : "19/8/2019-12:35", 
    "status" : "Pending"
}
{ 
    "_id" : ObjectId("5d83292c198c5e4168e729db"), 
    "uid" : NumberInt(1), 
    "orderid" : "345", 
    "date" : "19/8/2019-12:37", 
    "status" : "Pending"
}
{ 
    "_id" : ObjectId("5d832971368cdf2dd4aee8f6"), 
    "uid" : NumberInt(1), 
    "orderid" : "345", 
    "date" : "19/8/2019-12:38", 
    "status" : "Pending"
}
{ 
    "_id" : ObjectId("5d832a34368cdf2dd4aee8f8"), 
    "uid" : NumberInt(1), 
    "orderid" : "345", 
    "date" : "19/8/2019-12:41", 
    "status" : "Pending"
}
{ 
    "_id" : ObjectId("5d832b8a368cdf2dd4aee8f9"), 
    "uid" : NumberInt(1), 
    "orderid" : "345", 
    "date" : "19/8/2019-12:47", 
    "status" : "Pending"
}
{ 
    "_id" : ObjectId("5d832cb0e21c6d36c01b764d"), 
    "uid" : NumberInt(1), 
    "orderid" : "345", 
    "date" : "19/8/2019-12:52", 
    "status" : "Pending"
}
{ 
    "_id" : ObjectId("5d832d4ce790d11a18221463"), 
    "uid" : NumberInt(1), 
    "orderid" : "345", 
    "date" : "19/8/2019-12:55", 
    "status" : "Pending"
}
{ 
    "_id" : ObjectId("5d832deeb725e750287fc4bb"), 
    "uid" : NumberInt(1), 
    "orderid" : "345", 
    "date" : "19/8/2019-12:57", 
    "status" : "Pending"
}
{ 
    "_id" : ObjectId("5d832f975cf2ac4a801d6b38"), 
    "uid" : NumberInt(1), 
    "orderid" : "345", 
    "date" : "19/8/2019-13:4", 
    "status" : "Pending"
}
{ 
    "_id" : ObjectId("5d83342102c9e10d38f5bbfa"), 
    "uid" : NumberInt(1), 
    "orderid" : "345", 
    "date" : "19/8/2019-13:24", 
    "status" : "Pending"
}
{ 
    "_id" : ObjectId("5d83347b02c9e10d38f5bbff"), 
    "uid" : NumberInt(1), 
    "orderid" : "345", 
    "date" : "19/8/2019-13:25", 
    "status" : "Pending"
}
{ 
    "_id" : ObjectId("5d833c0802c9e10d38f5bc00"), 
    "uid" : NumberInt(1), 
    "orderid" : "345", 
    "date" : "19/8/2019-13:57", 
    "status" : "Pending"
}
{ 
    "_id" : ObjectId("5d834a544bfdc63f386e97d8"), 
    "uid" : NumberInt(1), 
    "orderid" : "345", 
    "date" : "19/8/2019-14:58", 
    "status" : "Pending"
}
{ 
    "_id" : ObjectId("5d834b1bd3d3964c2053aaeb"), 
    "uid" : NumberInt(1), 
    "orderid" : "345", 
    "date" : "19/8/2019-15:2", 
    "status" : "Pending"
}
{ 
    "_id" : ObjectId("5d834bd890f5aa56b0ed5de1"), 
    "uid" : NumberInt(1), 
    "orderid" : "345", 
    "date" : "19/8/2019-15:5", 
    "status" : "Pending"
}
{ 
    "_id" : ObjectId("5d834c623edbc708384aa59d"), 
    "uid" : NumberInt(1), 
    "orderid" : "345", 
    "date" : "19/8/2019-15:7", 
    "status" : "Pending"
}
{ 
    "_id" : ObjectId("5d834cc96285d92834344459"), 
    "uid" : NumberInt(1), 
    "orderid" : "345", 
    "date" : "19/8/2019-15:9", 
    "status" : "Pending"
}
{ 
    "_id" : ObjectId("5d85f3bdf82e643e6408271e"), 
    "uid" : NaN, 
    "orderid" : "345", 
    "date" : "21/8/2019-15:26", 
    "status" : "Pending"
}
